[{
	"year": 1984,
	"prizeList": [
		[{
			"name": "jan",
			"bio": "i'm a bio",
			"data": {
				"field": 0,
				"country": "FR",
				"gender": 1,
				"age": 50
			}
		}],
		[{
			"name": "jan",
			"bio": "i'm a bio",
			"data": {
				"field": 1,
				"country": "FR",
				"gender": 0,
				"age": 51
			}
		}, {
			"name": "jan",
			"bio": "i'm a bio",
			"data": {
				"field": 1,
				"country": "FR",
				"gender": 1,
				"age": 54
			}
		}],
		[{
			"name": "jan",
			"bio": "i'm a bio",
			"data": {
				"field": 2,
				"country": "FR",
				"gender": 0,
				"age": 43
			}
		}, {
			"name": "jan",
			"bio": "i'm a bio",
			"data": {
				"field": 2,
				"country": "FR",
				"gender": 1,
				"age": 33
			}
		}]
	]
}, {
	"year": 1998,
	"prizeList": [
		[],
		[],
		[{
			"name": "jan",
			"bio": "i'm a bio",
			"data": {
				"field": 2,
				"country": "FR",
				"gender": 0,
				"age": 53
			}
		}]
	]
}]